calculator_v/__init__.py
calculator_v/api_helper.py
calculator_v/calculator_v_client.py
calculator_v/configuration.py
calculator_v/decorators.py
calculator_v/controllers/__init__.py
calculator_v/controllers/base_controller.py
calculator_v/controllers/simple_calculator_controller.py
calculator_v/exceptions/__init__.py
calculator_v/exceptions/api_exception.py
calculator_v/http/__init__.py
calculator_v/http/http_call_back.py
calculator_v/http/http_client.py
calculator_v/http/http_context.py
calculator_v/http/http_method_enum.py
calculator_v/http/http_request.py
calculator_v/http/http_response.py
calculator_v/http/requests_client.py
calculator_v/models/__init__.py
calculator_v/models/operation_type_enum.py
tests/__init__.py
tests/http_response_catcher.py
tests/test_helper.py
tests/controllers/__init__.py
tests/controllers/controller_test_base.py
tests/controllers/test_simple_calculator_controller.py
calculator_v-1.dist-info/LICENSE
calculator_v-1.dist-info/METADATA
calculator_v-1.dist-info/WHEEL
calculator_v-1.dist-info/top_level.txt
calculator_v-1.dist-info/RECORD
